loracode/__init__.py
loracode/__main__.py
loracode/analytics.py
loracode/args.py
loracode/args_formatter.py
loracode/auto_approve.py
loracode/checkpoints.py
loracode/commands.py
loracode/context_files.py
loracode/copypaste.py
loracode/deprecated.py
loracode/diffs.py
loracode/dump.py
loracode/editor.py
loracode/encoding.py
loracode/exceptions.py
loracode/format_settings.py
loracode/gui.py
loracode/help.py
loracode/help_pats.py
loracode/history.py
loracode/hooks.py
loracode/i18n.py
loracode/io.py
loracode/linter.py
loracode/llm.py
loracode/lora_code_auth.py
loracode/lora_code_client.py
loracode/main.py
loracode/mdstream.py
loracode/models.py
loracode/onboarding.py
loracode/output_formats.py
loracode/prompts.py
loracode/reasoning_tags.py
loracode/repo.py
loracode/repomap.py
loracode/report.py
loracode/run_cmd.py
loracode/scrape.py
loracode/sendchat.py
loracode/special.py
loracode/urls.py
loracode/utils.py
loracode/versioncheck.py
loracode/voice.py
loracode/waiting.py
loracode/watch.py
loracode/watch_prompts.py
loracode/coders/__init__.py
loracode/coders/architect_coder.py
loracode/coders/architect_prompts.py
loracode/coders/ask_coder.py
loracode/coders/ask_prompts.py
loracode/coders/base_coder.py
loracode/coders/base_prompts.py
loracode/coders/chat_chunks.py
loracode/coders/context_coder.py
loracode/coders/context_prompts.py
loracode/coders/editblock_coder.py
loracode/coders/editblock_fenced_coder.py
loracode/coders/editblock_fenced_prompts.py
loracode/coders/editblock_func_coder.py
loracode/coders/editblock_func_prompts.py
loracode/coders/editblock_prompts.py
loracode/coders/editor_diff_fenced_coder.py
loracode/coders/editor_diff_fenced_prompts.py
loracode/coders/editor_editblock_coder.py
loracode/coders/editor_editblock_prompts.py
loracode/coders/editor_whole_coder.py
loracode/coders/editor_whole_prompts.py
loracode/coders/help_coder.py
loracode/coders/help_prompts.py
loracode/coders/patch_coder.py
loracode/coders/patch_prompts.py
loracode/coders/search_replace.py
loracode-0.1.2.dist-info/licenses/LICENSE
loracode-0.1.2.dist-info/METADATA
loracode-0.1.2.dist-info/WHEEL
loracode-0.1.2.dist-info/entry_points.txt
loracode-0.1.2.dist-info/top_level.txt
loracode-0.1.2.dist-info/RECORD
