Metadata-Version: 2.4
Name: loracode
Version: 0.1.2
Summary: AI-powered coding assistant in your terminal
Author-email: Lora Technologies <support@loratech.dev>
Maintainer-email: Lora Technologies <support@loratech.dev>
License: Apache-2.0
Project-URL: Homepage, https://github.com/Lora-Technologies/loracode
Project-URL: Documentation, https://github.com/Lora-Technologies/loracode#readme
Project-URL: Repository, https://github.com/Lora-Technologies/loracode.git
Project-URL: Issues, https://github.com/Lora-Technologies/loracode/issues
Project-URL: Changelog, https://github.com/Lora-Technologies/loracode/releases
Keywords: ai,coding,assistant,terminal,cli,llm,gpt,developer-tools,code-generation,pair-programming
Classifier: Development Status :: 4 - Beta
Classifier: Environment :: Console
Classifier: Intended Audience :: Developers
Classifier: License :: OSI Approved :: Apache Software License
Classifier: Operating System :: OS Independent
Classifier: Programming Language :: Python :: 3
Classifier: Programming Language :: Python :: 3.10
Classifier: Programming Language :: Python :: 3.11
Classifier: Programming Language :: Python :: 3.12
Classifier: Topic :: Software Development
Classifier: Topic :: Software Development :: Code Generators
Classifier: Topic :: Utilities
Requires-Python: >=3.10
License-File: LICENSE
Requires-Dist: pydub
Requires-Dist: configargparse
Requires-Dist: GitPython
Requires-Dist: jsonschema
Requires-Dist: rich
Requires-Dist: prompt_toolkit
Requires-Dist: backoff
Requires-Dist: pathspec
Requires-Dist: diskcache
Requires-Dist: grep_ast
Requires-Dist: packaging
Requires-Dist: sounddevice
Requires-Dist: soundfile
Requires-Dist: beautifulsoup4
Requires-Dist: PyYAML
Requires-Dist: diff-match-patch
Requires-Dist: pypandoc
Requires-Dist: litellm
Requires-Dist: flake8
Requires-Dist: importlib_resources
Requires-Dist: pyperclip
Requires-Dist: posthog
Requires-Dist: mixpanel
Requires-Dist: pexpect
Requires-Dist: json5
Requires-Dist: psutil
Requires-Dist: watchfiles
Requires-Dist: socksio
Requires-Dist: pillow
Requires-Dist: shtab
Requires-Dist: oslex
Requires-Dist: google-generativeai
Requires-Dist: networkx<3.5
Requires-Dist: scipy<1.16
Requires-Dist: importlib-metadata<8.0.0
Requires-Dist: python-dotenv
Provides-Extra: dev
Requires-Dist: pytest>=7.0; extra == "dev"
Requires-Dist: pytest-cov; extra == "dev"
Requires-Dist: pytest-env; extra == "dev"
Requires-Dist: pre-commit; extra == "dev"
Requires-Dist: black; extra == "dev"
Requires-Dist: isort; extra == "dev"
Requires-Dist: mypy; extra == "dev"
Provides-Extra: browser
Requires-Dist: streamlit; extra == "browser"
Provides-Extra: help
Requires-Dist: playwright; extra == "help"
Dynamic: license-file
